sdRDM/__init__.py
sdRDM/cli.py
sdRDM/base/__init__.py
sdRDM/base/datamodel.py
sdRDM/base/importemodules.py
sdRDM/base/listplus.py
sdRDM/base/utils.py
sdRDM/base/ioutils/__init__.py
sdRDM/base/ioutils/hdf5.py
sdRDM/base/ioutils/xml.py
sdRDM/database/__init__.py
sdRDM/database/utils.py
sdRDM/generator/__init__.py
sdRDM/generator/abstractparser.py
sdRDM/generator/codegen.py
sdRDM/generator/datatypes.py
sdRDM/generator/markdownparser.py
sdRDM/generator/mermaidclass.py
sdRDM/generator/mermaidenum.py
sdRDM/generator/mermaidexternal.py
sdRDM/generator/schemagen.py
sdRDM/generator/utils.py
sdRDM/generator/templates/__init__.py
sdRDM/generator/templates/add_method_template.jinja2
sdRDM/generator/templates/attribute_template.jinja2
sdRDM/generator/templates/class_template.jinja2
sdRDM/generator/templates/enum_template.jinja2
sdRDM/generator/templates/function_docstring.jinja2
sdRDM/generator/templates/import_template.jinja2
sdRDM/generator/templates/init_file_library.jinja2
sdRDM/generator/templates/init_file_template.jinja2
sdRDM/generator/templates/mermaid_class.jinja2
sdRDM/generator/templates/reference_template.jinja2
sdRDM/linking/__init__.py
sdRDM/linking/link.py
sdRDM/linking/nodes.py
sdRDM/linking/utils.py
sdRDM/tools/__init__.py
sdRDM/tools/gitutils.py
sdRDM/tools/utils.py
software_driven_RDM-0.0.3.dist-info/METADATA
software_driven_RDM-0.0.3.dist-info/WHEEL
software_driven_RDM-0.0.3.dist-info/entry_points.txt
software_driven_RDM-0.0.3.dist-info/top_level.txt
software_driven_RDM-0.0.3.dist-info/RECORD
